<?xml version="1.0" encoding="UTF-8"?>
<source name="zf_device_oled.c" location="c:\users\ch lee\desktop\youhua\libraries\zf_device" is_link="no">
 <warning>
 <file>c:\users\ch lee\desktop\youhua\libraries\zf_device\zf_device_oled.c</file>
  <method>oled_show_int</method>
  <lineNo>358</lineNo>
  <column>18</column>
  <checkName>ATH-div-0-unchk-local</checkName>
  <message>Local variable `offset&apos; is not checked against 0 before it is used as a divisor</message>
  <trace>
   <traceBlock line="358" file="c:\users\ch lee\desktop\youhua\libraries\zf_device\zf_device_oled.c" method="oled_show_int">
    <traceLine line="358" text="non_float_cast_divide" type="!"/>
    <traceLine line="334" text="return" type=" "/>
   </traceBlock>
  </trace>
  <rules></rules>
  <severity>Medium</severity>
 </warning>
 <warning>
 <file>c:\users\ch lee\desktop\youhua\libraries\zf_device\zf_device_oled.c</file>
  <method>oled_show_wave</method>
  <lineNo>647</lineNo>
  <column>73</column>
  <checkName>ATH-div-0-unchk-param</checkName>
  <message>Parameter `value_max&apos; is not checked against 0 before it is used as a divisor</message>
  <trace>
   <traceBlock line="647" file="c:\users\ch lee\desktop\youhua\libraries\zf_device\zf_device_oled.c" method="oled_show_wave">
    <traceLine line="647" text="non_float_cast_divide" type="!"/>
    <traceLine line="647" text="non_float_cast_divide" type="!"/>
    <traceLine line="620" text="return" type=" "/>
   </traceBlock>
  </trace>
  <rules></rules>
  <severity>Medium</severity>
 </warning>
</source>
